{
    "format_version": "1.12",
    "minecraft:recipe_shaped": {
      "description": {
      "identifier": "billey:sharksword"
      },
      "tags": [ "crafting_table" ],
      "group": "pickletrizer",
      "pattern": [
        "AAA",
        "AAA",
        " B "
      ],
      "key": {
        "B": {
          "item": "billey:orange_peel"
        },
        "A": {
          "item": "billey:shark_tooth"
        }
      },
      "result": {
       "item": "billey:shark_tooth_sword"
     }
    }
  }