{
  "format_version": "1.10.0",
  "minecraft:client_entity": {
    "description": {
      "identifier": "billey:duck",
      "materials": {
        "default": "skeleton",
        "skeleton": "skeleton",
        "dyeable": "cat",
        "cat": "cat"
      },
      "textures": {
        "white": "textures/entity/bill/duck",
        "brown": "textures/entity/bill/duck2",
        "golden": "textures/entity/bill/duck1",
        "whiteling": "textures/entity/bill/duck3",
        "brownling": "textures/entity/bill/duck4",
        "mandarin": "textures/entity/bill/duck12",
        "blue": "textures/entity/bill/duck14",
        "hatopy": "textures/entity/bill/hatopy",
        "black": "textures/entity/bill/duck15",
        "head": "textures/entity/bill/duck16",
        "whole": "textures/entity/bill/duck17",
        "leather": "textures/entity/bill/duckleather",
        "gold": "textures/entity/bill/duckgold",
        "chain": "textures/entity/bill/duckchain",
        "iron": "textures/entity/bill/duckiron",
        "diamond": "textures/entity/bill/duckdiamond",
        "chest": "textures/entity/bill/cuteduckchest",
        "endrodpetarmor": "textures/entity/bill/endrodarmor",
        "hat": "textures/entity/bill/hat",
        "netherite": "textures/entity/bill/ducknetherite",
        "centipedehat": "textures/entity/bill/centipedehat"
      },
      "geometry": {
        "default": "geometry.billduck",
        "hat": "geometry.billduckhat",
        "chest": "geometry.billduckchest",
        "armor": "geometry.billduckarmor",
        "endrod": "geometry.billduckendrod"
      },
      "particle_effects": {
        "zeelol": "billey:zeeduck"
      },
      "animations": {
        "hurt": "animation.billduck.hurt",
        "move": "animation.billduck.walk32",
        "sit": "animation.billduck.sit",
        "swim": "animation.billduck.swim",
        "look_at_target": "animation.billduck.look_at_target",
        "look_at_target_baby": "animation.billduckling.look_at_target",
        "baby_transform": "animation.billduck.ling",
        "flap_wings": "animation.billduck.fall",
        "quack": "animation.billduck.quack",
        "quackbaby": "animation.billduck.quackbaby",
        "sheared": "animation.billduck.flap",
        "eat": "animation.billduck.eat",
        "random_idle": "animation.billduck.wiggle_tail",
        "angry": "animation.billduck.angry",
        "diphead": "animation.billduck.pickupbread",
        "sleep": "animation.billduck.sleep",
        "sleeptl": "animation.billduck.sleep_particle",
        "gothurt": "animation.billduck.gothurt",
        "hitcont": "controller.animation.billey.hitanim",
        "controller.sit": "controller.animation.billey.sit_or_sleep",
        "controller.quack": "controller.animation.billey.quack",
        "controller.quackbaby": "controller.animation.billey.quackbaby",
        "controller.eat": "controller.animation.billey.eat",
        "controller.sheared": "controller.animation.billey.duckidleanim",
        "controller.swim": "controller.animation.billey.swimduck",
        "controller.sleep": "controller.animation.billey.sleep",
        "controller.random_idle_water": "controller.animation.billey.random_idle_water",
        "controller.random_idle": "controller.animation.billey.random_idle",
        "angrycon": "controller.animation.billey.duckangry",
        "new": "animation.billduckproj.body"
      },
      "sound_effects": {
        "quack": "billey.duck.say",
        "quackbaby": "billey.duck.saybaby"
      },
      "scripts": {
        "initialize": [
          "v.time_to_idle = 0;",
          "v.prevhealth = 0;"
        ],
        "animate": [
          {
            "hitcont": "!q.is_stunned"
          },
          "new",
          {
            "controller.sleep": "!q.is_sleeping"
          }, //v.state == 4 means sleeping with owner and q.is_sleeping is for sleeping randomly
          {
            "controller.sheared": "v.state != 4 && !q.is_sleeping"
          },
          {
            "controller.random_idle": "v.state != 4 && !q.is_sleeping"
          },
          {
            "controller.random_idle_water": "v.state != 4 && !q.is_sleeping"
          },
          {
            "hurt": "(q.health < q.max_health) && q.is_alive"
          },
          "angrycon",
          {
            "controller.sit": "!q.has_rider"
          },
          {
            "controller.eat": "!q.is_stunned && !q.is_sleeping"
          },
          {
            "controller.swim": "!q.has_rider"
          },
          {
            "look_at_target": "!q.is_baby ? 1 - v.attack_time"
          },
          {
            "controller.quack": "!q.is_baby && v.state != 4 && !q.has_target && !q.is_sleeping && q.health >= q.max_health"
          },
          {
            "controller.quackbaby": "q.is_baby && v.state != 4 && !q.has_target && !q.is_sleeping && q.health >= q.max_health"
          },
          {
            "look_at_target_baby": "q.is_baby - math.sin(v.attack_time * 180) * 4"
          },
          {
            "flap_wings": "!q.is_in_water && !q.has_rider && !q.is_on_ground"
          },
          {
            "move": "q.modified_move_speed"
          },
          {
            "baby_transform": "q.is_baby"
          }
        ]
      },
      "render_controllers": [
        "controller.render.billduck",
        {
          "controller.render.billduckarmor": "q.mark_variant > 0 && q.mark_variant != 7"
        },
        {
          "controller.render.billduckendrod": "q.mark_variant == 7"
        },
        {
          "controller.render.billbduckhat": "q.is_saddled"
        },
        {
          "controller.render.billduckchest": "q.is_chested"
        }
      ],
      "spawn_egg": {
        "base_color": "#5E4523",
        "overlay_color": "#193F0A"
      }
    }
  }
}